{"name":"alexandra_generic-food-database","title":"Generic Food Database","description":"Database of 900 common Foods. 4 columns, Name, Scientific name, Group, Sub-group. CSV","homepage":"https://data.world/alexandra/generic-food-database","license":"Public Domain","resources":[{"name":"generic_food","schema":{"fields":[{"name":"food_name","title":"FOOD NAME","type":"string","rdfType":"http://www.w3.org/2001/XMLSchema#string","dwSourceId":"food_name"},{"name":"scientific_name","title":"SCIENTIFIC NAME","type":"string","rdfType":"http://www.w3.org/2001/XMLSchema#string","dwSourceId":"scientific_name"},{"name":"group","title":"GROUP","type":"string","rdfType":"http://www.w3.org/2001/XMLSchema#string","dwSourceId":"group"},{"name":"sub_group","title":"SUB GROUP","type":"string","rdfType":"http://www.w3.org/2001/XMLSchema#string","dwSourceId":"sub_group"}]},"path":"data/generic_food.csv","format":"csv"},{"name":"original/generic-food.csv","path":"original/generic-food.csv","format":"csv","mediatype":"text/csv","bytes":46392}],"keywords":["food","foods","csv"]}